pygame_vkeyboard/DejaVuSans.ttf
pygame_vkeyboard/__init__.py
pygame_vkeyboard/vkeyboard.py
pygame_vkeyboard/vkeys.py
pygame_vkeyboard/vrenderers.py
pygame_vkeyboard/vtextinput.py
pygame_vkeyboard/examples/__init__.py
pygame_vkeyboard/examples/azerty.py
pygame_vkeyboard/examples/numeric.py
pygame_vkeyboard/examples/resize.py
pygame_vkeyboard/examples/textinput.py
pygame_vkeyboard-2.0.9.dist-info/LICENSE.txt
pygame_vkeyboard-2.0.9.dist-info/METADATA
pygame_vkeyboard-2.0.9.dist-info/WHEEL
pygame_vkeyboard-2.0.9.dist-info/top_level.txt
pygame_vkeyboard-2.0.9.dist-info/RECORD
