Metadata-Version: 2.1
Name: pygame-vkeyboard
Version: 2.0.9
Summary: Visual keyboard highly customizable for pygame.
Home-page: https://github.com/Faylixe/pygame-vkeyboard
Author: Felix Voituret, Antoine Rousseaux
Author-email: felix@voituret.fr, anxuae-prog@yahoo.fr
License: Apache License 2.0
Download-URL: https://pypi.org/project/pygame-vkeyboard/#files
Keywords: pygame,keyboard
Platform: UNKNOWN
Classifier: Programming Language :: Python :: 2
Classifier: Programming Language :: Python :: 3
Classifier: Topic :: Software Development :: Libraries :: pygame
Requires-Python: >=2.7
License-File: LICENSE.txt
